{"cameraMode":{"drawMode":0,"name":"Shaded","section":"Shading Mode"},"sceneLighting":false,"audioPlay":false,"sceneViewState":{"m_AlwaysRefresh":false,"showFog":true,"showSkybox":false,"showFlares":true,"showImageEffects":true,"showParticleSystems":true,"showVisualEffectGraphs":true,"m_FxEnabled":true},"in2DMode":false,"pivot":{"x":2.433734655380249,"y":-12.022683143615723,"z":4.077815055847168},"rotation":{"x":-0.36265772581100466,"y":0.41515809297561648,"z":-0.18532149493694306,"w":-0.8136593699455261},"size":9.233092308044434,"orthographic":false}